pigment/__init__.py
pigment/exceptions.py
pigment/vars.py
pigment-0.5.0.dist-info/LICENSE
pigment-0.5.0.dist-info/METADATA
pigment-0.5.0.dist-info/WHEEL
pigment-0.5.0.dist-info/top_level.txt
pigment-0.5.0.dist-info/RECORD
