Metadata-Version: 2.1
Name: pigment
Version: 0.5.0
Summary: Python utilities for colors
Home-page: https://pigment.readthedocs.io/
Author: Ben Soyka
Author-email: bensoyka@icloud.com
License: UNKNOWN
Project-URL: Source, https://github.com/bsoyka/pigment
Project-URL: Changelog, https://github.com/bsoyka/pigment/releases
Platform: UNKNOWN
Classifier: License :: OSI Approved :: MIT License
Classifier: Operating System :: OS Independent
Classifier: Intended Audience :: Developers
Classifier: Natural Language :: English
Classifier: Programming Language :: Python
Classifier: Programming Language :: Python :: 3
Classifier: Programming Language :: Python :: 3.5
Classifier: Programming Language :: Python :: 3.6
Classifier: Programming Language :: Python :: 3.7
Classifier: Programming Language :: Python :: 3.8
Classifier: Programming Language :: Python :: 3.9
Requires-Python: >=3.5
Requires-Dist: averager (==2.0.1)
